Ecode/__main__.py
ecode_cmd-3.1.dist-info/METADATA
ecode_cmd-3.1.dist-info/WHEEL
ecode_cmd-3.1.dist-info/entry_points.txt
ecode_cmd-3.1.dist-info/top_level.txt
ecode_cmd-3.1.dist-info/RECORD
