Metadata-Version: 2.4
Name: Ecode-cmd
Version: 3.1
Summary: A cool command-line tool with multiple features.
Author: AmiraliBatman
Requires-Python: >=3.10
Requires-Dist: pyttsx3>=2.5
Requires-Dist: termcolor>=1.1
Requires-Dist: datetime
Requires-Dist: flask
Dynamic: author
Dynamic: description
Dynamic: description-content-type
Dynamic: requires-dist
Dynamic: requires-python
Dynamic: summary
